setup.py
src/digimat/__init__.py
src/digimat.blink1.egg-info/PKG-INFO
src/digimat.blink1.egg-info/SOURCES.txt
src/digimat.blink1.egg-info/dependency_links.txt
src/digimat.blink1.egg-info/namespace_packages.txt
src/digimat.blink1.egg-info/not-zip-safe
src/digimat.blink1.egg-info/requires.txt
src/digimat.blink1.egg-info/top_level.txt
src/digimat/blink1/__init__.py
src/digimat/blink1/blink1.py
src/digimat/blink1/kelvin.py