Metadata-Version: 1.0
Name: digimat.blink1
Version: 0.1.3
Summary: Digimat Blink1
Home-page: UNKNOWN
Author: Frederic Hess
Author-email: fhess@splust.ch
License: PSF
Platform: UNKNOWN
